{
  "main": {
    "id": "e2998a998d19a35c",
    "type": "split",
    "children": [
      {
        "id": "f6f6d13d9d650e1f",
        "type": "tabs",
        "children": [
          {
            "id": "c7647adfe4d5446c",
            "type": "leaf",
            "state": {
              "type": "markdown",
              "state": {
                "file": "Java/POO - Parte 1/Enumerações e composições/Enumerações e composições.md",
                "mode": "source",
                "backlinks": false,
                "source": false
              }
            }
          },
          {
            "id": "cddef6125cc94b4b",
            "type": "leaf",
            "state": {
              "type": "markdown",
              "state": {
                "file": "Java/Resumos/POO/Composição.md",
                "mode": "source",
                "backlinks": false,
                "source": false
              }
            }
          },
          {
            "id": "606df1797edaa4a1",
            "type": "leaf",
            "state": {
              "type": "markdown",
              "state": {
                "file": "Java/POO - Parte 1/Materiais de apoio.md",
                "mode": "preview",
                "backlinks": false,
                "source": false
              }
            }
          }
        ]
      }
    ],
    "direction": "vertical"
  },
  "left": {
    "id": "bab9f049853e3f48",
    "type": "split",
    "children": [
      {
        "id": "243be64d43ed276f",
        "type": "tabs",
        "children": [
          {
            "id": "02ec1759d8be77b6",
            "type": "leaf",
            "state": {
              "type": "file-explorer",
              "state": {
                "sortOrder": "alphabetical"
              }
            }
          },
          {
            "id": "4fb6abb64ffa0b93",
            "type": "leaf",
            "state": {
              "type": "search",
              "state": {
                "query": "tag:#This",
                "matchingCase": false,
                "explainSearch": false,
                "collapseAll": false,
                "extraContext": false,
                "sortOrder": "alphabetical"
              }
            }
          },
          {
            "id": "69cb83e5082bd46b",
            "type": "leaf",
            "state": {
              "type": "bookmarks",
              "state": {}
            }
          }
        ]
      }
    ],
    "direction": "horizontal",
    "width": 200
  },
  "right": {
    "id": "e4ddb5f6fce3a050",
    "type": "split",
    "children": [
      {
        "id": "2aa53593cd00e725",
        "type": "tabs",
        "children": [
          {
            "id": "983a119d396bf840",
            "type": "leaf",
            "state": {
              "type": "outgoing-link",
              "state": {
                "file": "Java/POO - Parte 1/Enumerações e composições/Enumerações e composições.md",
                "linksCollapsed": false,
                "unlinkedCollapsed": true
              }
            }
          },
          {
            "id": "aad37825fc8daaf6",
            "type": "leaf",
            "state": {
              "type": "tag",
              "state": {
                "sortOrder": "frequency",
                "useHierarchy": true
              }
            }
          },
          {
            "id": "bf774246f83733ce",
            "type": "leaf",
            "state": {
              "type": "outline",
              "state": {
                "file": "Java/POO - Parte 1/Enumerações e composições/Enumerações e composições.md"
              }
            }
          },
          {
            "id": "ec1e1e28e8f1f2f0",
            "type": "leaf",
            "state": {
              "type": "advanced-tables-toolbar",
              "state": {}
            }
          }
        ],
        "currentTab": 3
      }
    ],
    "direction": "horizontal",
    "width": 300,
    "collapsed": true
  },
  "left-ribbon": {
    "hiddenItems": {
      "graph:Abrir visualização em gráfico": false,
      "switcher:Abrir a troca rápida": true,
      "canvas:Criar novo canvas": false,
      "daily-notes:Abrir a nota de hoje": true,
      "templates:Inserir modelo": true,
      "command-palette:Abrir paleta de comandos": false,
      "table-editor-obsidian:Advanced Tables Toolbar": false,
      "obsidian-excalidraw-plugin:Create new drawing": false,
      "markdown-importer:Abrir importador Markdown": false
    }
  },
  "active": "c7647adfe4d5446c",
  "lastOpenFiles": [
    "Java/POO - Parte 1/Materiais de apoio.md",
    "Java/POO - Parte 1/Enumerações e composições/Enumerações e composições.md",
    "PDFs e imgs/worker.jpg",
    "Java/Resumos/POO/Composição.md",
    "PDFs e imgs/services.jpg",
    "PDFs e imgs/entities.jpg",
    "PDFs e imgs/06-estruturas-repetitivas.pdf",
    "PDFs e imgs/07-enumeracoes-composicao.pdf",
    "PDFs e imgs/07-outros-topicos-basicos.pdf",
    "PDFs e imgs/boxing.jpg",
    "PDFs e imgs/Capturar.jpg",
    "PDFs e imgs/Capturar2.jpg",
    "PDFs e imgs/Classes_referencias.jpg",
    "PDFs e imgs/Classes_referencias 1.jpg",
    "PDFs e imgs/Contribuindo em um Projeto Open Source no GitHub.pdf",
    "PDFs e imgs/Curso-Java-COMPLETO.pdf",
    "PDFs e imgs/Curso-Java-COMPLETO 1.pdf",
    "PDFs e imgs/data-hora.jpg",
    "PDFs e imgs/date-calendar.pdf",
    "PDFs e imgs/desalocaçãoEscopo.jpg",
    "PDFs e imgs/git-guia-basico.pdf",
    "PDFs e imgs/introducao-linguagem-java 1.pdf",
    "Java/POO - Parte 1/Enumerações e composições/Design.md",
    "PDFs e imgs/Diagram 4.svg.xml",
    "Roteiro de estudos/Roteiro.md",
    "Anotações_cursos_2/Java-Dio/Métodos.md",
    "Livros/As 48 leis do poder/Lei 4.md",
    "Livros/As 48 leis do poder/Lei 3.md",
    "Livros/As 48 leis do poder/Lei 2.md",
    "Livros/As 48 leis do poder/Lei 1.md",
    "Java/Resumos/POO/data-hora.md",
    "Java/POO - Parte 1/data-hora/timezone, ISO8601 instanciando e convertendo.md",
    "Java/POO - Parte 1/data-hora/Operações com data-hora.md",
    "Java/POO - Parte 1/data-hora/Introdução.md",
    "Anotações_cursos_2/Java-Dio/Terminal e Argumentos.md",
    "Java/POO - Parte 1/memória, arrays e listas/Matrizes.md",
    "Java/POO - Parte 1/memória, arrays e listas/Vetores.md",
    "Java/POO - Parte 1/memória, arrays e listas/Listas.md",
    "Java/Resumos/POO/Listas.md",
    "Listas.md",
    "Java/POO - Parte 1/memória, arrays e listas/for each.md",
    "for each.md",
    "Java/POO - Parte 1/memória, arrays e listas/Tipos referência vs tipo valor, garbage collector e escopo local.md",
    "Java/POO - Parte 1/memória, arrays e listas/Garbage collector e escopo local.md",
    "Java/POO - Parte 1/memória, arrays e listas/Boxing, unboxing, wrapper e for each.md"
  ]
}