{
  "main": {
    "id": "e51313a2e7e491a3",
    "type": "split",
    "children": [
      {
        "id": "f0eaa891ba73d800",
        "type": "tabs",
        "children": [
          {
            "id": "021b9483400e3740",
            "type": "leaf",
            "state": {
              "type": "markdown",
              "state": {
                "file": "Java/Lógica_Algoritmos_Java/Estrutura Sequencial/Expressões Aritméticas.md",
                "mode": "source",
                "source": false
              }
            }
          },
          {
            "id": "10063a1cac8c8593",
            "type": "leaf",
            "state": {
              "type": "markdown",
              "state": {
                "file": "Java/Lógica_Algoritmos_Java/Estrutura Sequencial/Variáveis e tipos básicos em Java.md",
                "mode": "source",
                "source": false
              }
            }
          },
          {
            "id": "8eaf14568fe22a6c",
            "type": "leaf",
            "state": {
              "type": "markdown",
              "state": {
                "file": "Java/Lógica_Algoritmos_Java/Materiais de apoio.md",
                "mode": "source",
                "source": false
              }
            }
          },
          {
            "id": "a9b19862430aa375",
            "type": "leaf",
            "state": {
              "type": "graph",
              "state": {}
            }
          }
        ],
        "currentTab": 2
      }
    ],
    "direction": "vertical"
  },
  "left": {
    "id": "d20057fdd7e81e82",
    "type": "split",
    "children": [
      {
        "id": "7c4f18339223f762",
        "type": "tabs",
        "children": [
          {
            "id": "503ba964d621ca23",
            "type": "leaf",
            "state": {
              "type": "file-explorer",
              "state": {
                "sortOrder": "alphabetical"
              }
            }
          },
          {
            "id": "7f0dd0a929bb23af",
            "type": "leaf",
            "state": {
              "type": "search",
              "state": {
                "query": "tag:#Compilação",
                "matchingCase": false,
                "explainSearch": false,
                "collapseAll": false,
                "extraContext": false,
                "sortOrder": "alphabetical"
              }
            }
          },
          {
            "id": "463860d5cac3ca7f",
            "type": "leaf",
            "state": {
              "type": "bookmarks",
              "state": {}
            }
          }
        ]
      }
    ],
    "direction": "horizontal",
    "width": 200
  },
  "right": {
    "id": "0163a8b2d06de4ba",
    "type": "split",
    "children": [
      {
        "id": "cba041e2435ba17e",
        "type": "tabs",
        "children": [
          {
            "id": "d420fed0fbbddc01",
            "type": "leaf",
            "state": {
              "type": "backlink",
              "state": {
                "file": "Java/Lógica_Algoritmos_Java/Materiais de apoio.md",
                "collapseAll": false,
                "extraContext": false,
                "sortOrder": "alphabetical",
                "showSearch": false,
                "searchQuery": "",
                "backlinkCollapsed": false,
                "unlinkedCollapsed": true
              }
            }
          },
          {
            "id": "53ea41f2c92d98bf",
            "type": "leaf",
            "state": {
              "type": "outgoing-link",
              "state": {
                "file": "Java/Lógica_Algoritmos_Java/Materiais de apoio.md",
                "linksCollapsed": false,
                "unlinkedCollapsed": true
              }
            }
          },
          {
            "id": "5fc7abf5123f01a2",
            "type": "leaf",
            "state": {
              "type": "tag",
              "state": {
                "sortOrder": "frequency",
                "useHierarchy": true
              }
            }
          },
          {
            "id": "9f60f993aec9aebe",
            "type": "leaf",
            "state": {
              "type": "outline",
              "state": {
                "file": "Java/Lógica_Algoritmos_Java/Materiais de apoio.md"
              }
            }
          }
        ]
      }
    ],
    "direction": "horizontal",
    "width": 300,
    "collapsed": true
  },
  "left-ribbon": {
    "hiddenItems": {
      "switcher:Abrir a troca rápida": false,
      "graph:Abrir visualização em gráfico": false,
      "canvas:Criar novo canvas": false,
      "daily-notes:Abrir a nota de hoje": false,
      "templates:Inserir modelo": false,
      "command-palette:Abrir paleta de comandos": false,
      "notion-like-tables:Create loom": false
    }
  },
  "active": "8eaf14568fe22a6c",
  "lastOpenFiles": [
    "Java/Lógica_Algoritmos_Java/Estrutura Sequencial/Variáveis e tipos básicos em Java.md",
    "Java/Lógica_Algoritmos_Java/Estrutura Sequencial/Expressões Aritméticas.md",
    "Java/Lógica_Algoritmos_Java/Materiais de apoio.md",
    "Java/Lógica_Algoritmos_Java/Conceitos/Introdução a linguagem Java.md",
    "Untitled.loom",
    "Untitled 1.loom",
    "Java/Lógica_Algoritmos_Java/Conceitos/Conceitos de Programação.md",
    "Java/Lógica_Algoritmos_Java/Conceitos",
    "Java/Lógica_Algoritmos_Java/Estrutura Sequencial",
    "PDFs e imgs/04-estrutura-sequencial (1).pdf",
    "AWS/Visão geral de nuvem/Seção 2 - Vantagens da computação em nuvem.md",
    "AWS/Visão geral de nuvem/Seção 1 - Introdução a computação em nuvem.md",
    "AWS/Visão geral de nuvem",
    "AWS",
    "Pasted image 20240903164405.png",
    "PDFs e imgs/introducao-linguagem-java 1.pdf",
    "introducao-linguagem-java.pdf",
    "Java/Lógica_Algoritmos_Java",
    "Roteiro de estudos/Roteiro.md",
    "Anotações_cursos_2/Java-Dio/Tipos e variáveis.md",
    "Anotações_cursos_2/Java-Dio/Terminal e Argumentos.md",
    "Anotações_cursos_2/Java-Dio/Palavras Reservadas.md",
    "Anotações_cursos_2/Java-Dio/Operadores.md",
    "Anotações_cursos_2/Java-Dio/Métodos.md",
    "Anotações_cursos_2/Java-Dio/Java Doc.md",
    "Anotações_cursos_2/Java-Dio/Introdução ao java.md",
    "Anotações_cursos_2/Java-Dio/Anatomia das Classes.md",
    "Anotações_cursos_2/Java-Dio/Escopo.md",
    "Anotações_cursos_2/Java-Dio/Escopo.md",
    "Mapas Mentais Python/Mapa mental Tratamento de Erro e Exceção.md",
    "Mapas Mentais Python/Mapa mental operadores de lógicos.md",
    "Python/while, break e continue.md",
    "Python/Concatenação.md",
    "Mapas Mentais Python/Atalhos vscode.md",
    "MySQL/O que é um Banco de Dados.md",
    "Python/Tratamento de erros e exceções.md",
    "Python/Modularização e Pacotes.md",
    "PDFs e imgs/Pasted image 20240820001633.png",
    "PDFs e imgs/Pasted image 20240820001556.png",
    "Icon.jpeg"
  ]
}